[{"id":1,"username":"admin","name":"admin","admin":true,"password":"admin","cart":{"items":[{"id":3,"name":"Lava Lamp","description":"A decorative coral lava lamp","price":8.99,"picture":null,"quantity":180},{"id":3,"name":"Lava Lamp","description":"A decorative coral lava lamp","price":8.99,"picture":null,"quantity":179},{"id":3,"name":"Lava Lamp","description":"A decorative coral lava lamp","price":8.99,"picture":null,"quantity":178},{"id":3,"name":"Lava Lamp","description":"A decorative coral lava lamp","price":8.99,"picture":null,"quantity":177},{"id":3,"name":"Lava Lamp","description":"A decorative coral lava lamp","price":8.99,"picture":null,"quantity":176}]}},{"id":2,"username":"bah8454","name":"bah8454","admin":false,"password":"password","cart":{"items":[{"id":9,"name":"Tablet","description":"zoooooom","price":99.0,"picture":null,"quantity":2},{"id":9,"name":"Tablet","description":"zoooooom","price":99.0,"picture":null,"quantity":1},{"id":9,"name":"Tablet","description":"zoooooom","price":99.0,"picture":null,"quantity":0},{"id":9,"name":"Tablet","description":"zoooooom","price":99.0,"picture":null,"quantity":4},{"id":9,"name":"Tablet","description":"zoooooom","price":99.0,"picture":null,"quantity":3},{"id":9,"name":"Tablet","description":"zoooooom","price":99.0,"picture":null,"quantity":2},{"id":9,"name":"Tablet","description":"zoooooom","price":99.0,"picture":null,"quantity":1}]}},{"id":3,"username":"adminb","name":"adminb","admin":false,"password":"admin","cart":{"items":[]}},{"id":4,"username":"adminbc","name":"adminbc","admin":false,"password":"admin","cart":{"items":[]}},{"id":5,"username":"adminc","name":"adminc","admin":false,"password":"admin","cart":{"items":[]}},{"id":6,"username":"adminbb","name":"adminbb","admin":false,"password":"admin","cart":{"items":[]}},{"id":7,"username":"adminss","name":"adminss","admin":false,"password":"admin","cart":{"items":[{"id":3,"name":"New Product","description":"Product Description","price":8.0,"picture":"/assets/car.png","quantity":75},{"id":8,"name":"Thing","description":"Majig","price":5.66,"picture":null,"quantity":0},{"id":3,"name":"New Product","description":"Product Description","price":8.0,"picture":"/assets/car.png","quantity":100}]}},{"id":8,"username":"adminkkk","name":"adminkkk","admin":false,"password":"admin","cart":{"items":[{"id":3,"name":"New Product","description":"Product Description","price":8.0,"picture":"/assets/car.png","quantity":105}]}}]